{
  "api": {
    "AdminQueries": {
      "authorizationType": "AMAZON_COGNITO_USER_POOLS",
      "dependsOn": [
        {
          "attributes": [
            "UserPoolId"
          ],
          "category": "auth",
          "resourceName": "EvryDay"
        },
        {
          "attributes": [
            "Arn",
            "Name"
          ],
          "category": "function",
          "resourceName": "AdminQueriesf3d0d774"
        }
      ],
      "providerPlugin": "awscloudformation",
      "service": "API Gateway"
    },
    "evryday": {
      "dependsOn": [],
      "output": {
        "authConfig": {
          "additionalAuthenticationProviders": [],
          "defaultAuthentication": {
            "apiKeyConfig": {
              "apiKeyExpirationDays": 7
            },
            "authenticationType": "API_KEY"
          }
        }
      },
      "providerPlugin": "awscloudformation",
      "service": "AppSync"
    }
  },
  "auth": {
    "EvryDay": {
      "customAuth": false,
      "dependsOn": [
        {
          "attributes": [
            "Arn",
            "Name"
          ],
          "category": "function",
          "resourceName": "EvryDayPostConfirmation",
          "triggerProvider": "Cognito"
        }
      ],
      "frontendAuthConfig": {
        "mfaConfiguration": "OFF",
        "mfaTypes": [
          "SMS"
        ],
        "passwordProtectionSettings": {
          "passwordPolicyCharacters": [],
          "passwordPolicyMinLength": 8
        },
        "signupAttributes": [
          "BIRTHDATE",
          "GENDER",
          "NAME"
        ],
        "socialProviders": [],
        "usernameAttributes": [
          "EMAIL"
        ],
        "verificationMechanisms": [
          "EMAIL"
        ]
      },
      "providerPlugin": "awscloudformation",
      "service": "Cognito"
    },
    "userPoolGroups": {
      "dependsOn": [
        {
          "attributes": [
            "UserPoolId",
            "AppClientIDWeb",
            "AppClientID"
          ],
          "category": "auth",
          "resourceName": "EvryDay"
        }
      ],
      "providerPlugin": "awscloudformation",
      "service": "Cognito-UserPool-Groups"
    }
  },
  "function": {
    "AdminQueriesf3d0d774": {
      "build": true,
      "dependsOn": [
        {
          "attributes": [
            "UserPoolId"
          ],
          "category": "auth",
          "resourceName": "EvryDay"
        }
      ],
      "providerPlugin": "awscloudformation",
      "service": "Lambda"
    },
    "EvryDayPostConfirmation": {
      "build": true,
      "providerPlugin": "awscloudformation",
      "service": "Lambda"
    }
  },
  "parameters": {
    "AMPLIFY_function_AdminQueriesf3d0d774_deploymentBucketName": {
      "usedBy": [
        {
          "category": "function",
          "resourceName": "AdminQueriesf3d0d774"
        }
      ]
    },
    "AMPLIFY_function_AdminQueriesf3d0d774_s3Key": {
      "usedBy": [
        {
          "category": "function",
          "resourceName": "AdminQueriesf3d0d774"
        }
      ]
    },
    "AMPLIFY_function_EvryDayPostConfirmation_GROUP": {
      "usedBy": [
        {
          "category": "function",
          "resourceName": "EvryDayPostConfirmation"
        }
      ]
    },
    "AMPLIFY_function_EvryDayPostConfirmation_deploymentBucketName": {
      "usedBy": [
        {
          "category": "function",
          "resourceName": "EvryDayPostConfirmation"
        }
      ]
    },
    "AMPLIFY_function_EvryDayPostConfirmation_s3Key": {
      "usedBy": [
        {
          "category": "function",
          "resourceName": "EvryDayPostConfirmation"
        }
      ]
    }
  }
}